ak_construct-2.5.2.dist-info/DESCRIPTION.rst
ak_construct-2.5.2.dist-info/METADATA
ak_construct-2.5.2.dist-info/RECORD
ak_construct-2.5.2.dist-info/WHEEL
ak_construct-2.5.2.dist-info/metadata.json
ak_construct-2.5.2.dist-info/top_level.txt
construct/__init__.py
construct/adapters.py
construct/core.py
construct/debug.py
construct/macros.py
construct/version.py
construct/formats/__init__.py
construct/formats/data/__init__.py
construct/formats/data/cap.py
construct/formats/data/snoop.py
construct/formats/executable/__init__.py
construct/formats/executable/elf32.py
construct/formats/executable/pe32.py
construct/formats/filesystem/__init__.py
construct/formats/filesystem/ext2.py
construct/formats/filesystem/fat16.py
construct/formats/filesystem/mbr.py
construct/formats/graphics/__init__.py
construct/formats/graphics/bmp.py
construct/formats/graphics/emf.py
construct/formats/graphics/gif.py
construct/formats/graphics/png.py
construct/formats/graphics/wmf.py
construct/lib/__init__.py
construct/lib/binary.py
construct/lib/bitstream.py
construct/lib/container.py
construct/lib/expr.py
construct/lib/hex.py
construct/lib/py3compat.py
construct/protocols/__init__.py
construct/protocols/ipstack.py
construct/protocols/application/__init__.py
construct/protocols/application/dns.py
construct/protocols/layer2/__init__.py
construct/protocols/layer2/arp.py
construct/protocols/layer2/ethernet.py
construct/protocols/layer2/mtp2.py
construct/protocols/layer3/__init__.py
construct/protocols/layer3/dhcpv4.py
construct/protocols/layer3/dhcpv6.py
construct/protocols/layer3/icmpv4.py
construct/protocols/layer3/igmpv2.py
construct/protocols/layer3/ipv4.py
construct/protocols/layer3/ipv6.py
construct/protocols/layer3/mtp3.py
construct/protocols/layer4/__init__.py
construct/protocols/layer4/isup.py
construct/protocols/layer4/tcp.py
construct/protocols/layer4/udp.py
